maruti/__init__.py
maruti/kaggle.py
maruti/sizes.py
maruti/utils.py
maruti/deepfake/__init__.py
maruti/deepfake/dataset.py
maruti/deepfake/models.py
maruti/deepfake/utils.py
maruti/deepfake/data/kaggle/cookies.txt
maruti/imports/__init__.py
maruti/imports/general.py
maruti/imports/ml.py
maruti/torch/__init__.py
maruti/torch/callback.py
maruti/torch/metrics.py
maruti/torch/utils.py
maruti/vision/__init__.py
maruti/vision/image.py
maruti/vision/video.py
maruti-1.3.4.dist-info/LICENSE
maruti-1.3.4.dist-info/METADATA
maruti-1.3.4.dist-info/WHEEL
maruti-1.3.4.dist-info/top_level.txt
maruti-1.3.4.dist-info/RECORD
