Metadata-Version: 2.1
Name: maruti
Version: 1.3.4
Summary: Maruti Library
Home-page: https://github.com/ankitsainidev/maruti
Author: Ankit Saini
Author-email: ankitsaini100205@gmail.com
License: UNKNOWN
Download-URL: https://github.com/ankitsainidev/maruti/archive/v1.3.tar.gz
Platform: UNKNOWN
Classifier: Programming Language :: Python :: 3
Classifier: License :: OSI Approved :: MIT License
Classifier: Operating System :: OS Independent
Requires-Python: >=3.5
Requires-Dist: tqdm (==4.40.2)
Requires-Dist: opencv-python
Requires-Dist: facenet-pytorch
